cd362c02a976e3f243f34cc25622d35a/__init__.py
cd362c02a976e3f243f34cc25622d35a/animev2.py
cd362c02a976e3f243f34cc25622d35a/app.py
cd362c02a976e3f243f34cc25622d35a/flux.py
cd362c02a976e3f243f34cc25622d35a/flux_pro.py
cd362c02a976e3f243f34cc25622d35a/klogin.py
cd362c02a976e3f243f34cc25622d35a/kreg.py
cd362c02a976e3f243f34cc25622d35a/linearv1.py
cd362c02a976e3f243f34cc25622d35a/logs.py
cd362c02a976e3f243f34cc25622d35a/pic_login.py
cd362c02a976e3f243f34cc25622d35a/pic_reg.py
cd362c02a976e3f243f34cc25622d35a/ponyv6.py
cd362c02a976e3f243f34cc25622d35a/realisticv2.py
cd362c02a976e3f243f34cc25622d35a/remove.py
cd362c02a976e3f243f34cc25622d35a/upscaler.py
gradio_uploader_12599-1.4.0.dist-info/LICENSE
gradio_uploader_12599-1.4.0.dist-info/METADATA
gradio_uploader_12599-1.4.0.dist-info/WHEEL
gradio_uploader_12599-1.4.0.dist-info/top_level.txt
gradio_uploader_12599-1.4.0.dist-info/RECORD
